{
  "metric": "datagrid-100k",
  "measuredAt": "2026-07-12T06:23:54.956Z",
  "version": "4.2.0+main",
  "rowCount": 10000,
  "rowCountNote": "10,000 rows on every automated run, not a literal 100,000 — this project's docs WASM app is a large, non-AOT-compiled (interpreter-tier) build. Two things were measured by hand against it and are reported here rather than re-run on every pass: (1) materializing 100k PerfRow instances plus DataGrid's client-side sort/search indices reliably hits the wasm32 linear-memory ceiling, reproduced even after raising WasmInitialHeapSize/EmccMaximumHeapSize to ~3.5 GB/~3.75 GB in Lumeo.Docs.csproj (right up against wasm32's 4 GB hard limit); (2) at 75k rows (the largest size that fit), the FIRST render alone took roughly a minute of wall clock, confirmed twice. A genuinely 100k+ row CLIENT dataset should use DataGrid's Virtualized + OnRangeRequest server-mode path instead of materializing every row in one in-memory List — see /components/datagrid.",
  "manuallyMeasuredScaleCeiling": {
    "rows_100000": "OOM (System.OutOfMemoryException) even at ~3.75 GB WASM heap ceiling",
    "rows_75000_firstRenderSeconds": "~60 (measured twice, non-AOT interpreter)"
  },
  "runs": [
    {
      "initialRenderMs": 5107.900000095367,
      "scrollFps": 56.07024322681297,
      "sortMs": 252.5,
      "filterMs": 334.7999999523163,
      "rowCountText": "10000 rows"
    },
    {
      "initialRenderMs": 5402.400000095367,
      "scrollFps": 55.08308693488192,
      "sortMs": 263.5,
      "filterMs": 357.7000000476837,
      "rowCountText": "10000 rows"
    },
    {
      "initialRenderMs": 5171.600000143051,
      "scrollFps": 55.167447721584416,
      "sortMs": 260.7000000476837,
      "filterMs": 341.2999999523163,
      "rowCountText": "10000 rows"
    },
    {
      "initialRenderMs": 5397.399999856949,
      "scrollFps": 53.1182372614598,
      "sortMs": 267.80000019073486,
      "filterMs": 320.39999985694885,
      "rowCountText": "10000 rows"
    },
    {
      "initialRenderMs": 5117.799999952316,
      "scrollFps": 58.03762018213974,
      "sortMs": 247.20000004768372,
      "filterMs": 343.5,
      "rowCountText": "10000 rows"
    }
  ],
  "machine": {
    "platform": "win32",
    "arch": "x64",
    "cpuModel": "AMD Ryzen 7 7800X3D 8-Core Processor           ",
    "cpuCores": 16,
    "totalMemGiB": 31.1,
    "nodeVersion": "v24.7.0",
    "browser": "149.0.7827.55"
  },
  "medians": {
    "initialRenderMs": 5171.600000143051,
    "scrollFps": 55.167447721584416,
    "sortMs": 260.7000000476837,
    "filterMs": 341.2999999523163
  }
}
