{
  "name": "Collapsible",
  "category": "Navigation",
  "subcategory": null,
  "description": "Single expandable region with animated height transition.",
  "thumbnail": "/preview-cards/collapsible.png",
  "hasDocsPage": true,
  "nugetPackage": "Lumeo",
  "files": [
    "UI/Collapsible/Collapsible.razor",
    "UI/Collapsible/CollapsibleContent.razor",
    "UI/Collapsible/CollapsibleTrigger.razor"
  ],
  "dependencies": [],
  "packageDependencies": [],
  "cssVars": [
    "--color-ring",
    "--radius"
  ],
  "api": {
    "name": "Collapsible",
    "category": "Navigation",
    "subcategory": null,
    "description": "Single expandable region with animated height transition.",
    "nugetPackage": "Lumeo",
    "files": [
      "UI/Collapsible/Collapsible.razor",
      "UI/Collapsible/CollapsibleContent.razor",
      "UI/Collapsible/CollapsibleTrigger.razor"
    ],
    "namespace": "Lumeo",
    "inheritsFrom": null,
    "implements": [],
    "parameters": [
      {
        "name": "ChildContent",
        "type": "RenderFragment?",
        "default": null,
        "description": null,
        "isCascading": false,
        "captureUnmatched": false
      },
      {
        "name": "Open",
        "type": "bool",
        "default": null,
        "description": null,
        "isCascading": false,
        "captureUnmatched": false
      },
      {
        "name": "OpenChanged",
        "type": "EventCallback<bool>",
        "default": null,
        "description": null,
        "isCascading": false,
        "captureUnmatched": false
      },
      {
        "name": "IsOpen",
        "type": "bool",
        "default": null,
        "description": null,
        "isCascading": false,
        "captureUnmatched": false
      },
      {
        "name": "IsOpenChanged",
        "type": "EventCallback<bool>",
        "default": null,
        "description": null,
        "isCascading": false,
        "captureUnmatched": false
      },
      {
        "name": "Class",
        "type": "string?",
        "default": null,
        "description": null,
        "isCascading": false,
        "captureUnmatched": false
      },
      {
        "name": "AdditionalAttributes",
        "type": "Dictionary<string, object>?",
        "default": null,
        "description": null,
        "isCascading": false,
        "captureUnmatched": true
      }
    ],
    "events": [
      {
        "name": "OpenChanged",
        "type": "EventCallback<bool>",
        "description": null
      },
      {
        "name": "IsOpenChanged",
        "type": "EventCallback<bool>",
        "description": null
      }
    ],
    "enums": [],
    "records": [
      {
        "name": "CollapsibleContext",
        "signature": "CollapsibleContext(bool IsOpen, EventCallback Toggle)",
        "description": null
      }
    ],
    "cssVars": [
      "--color-ring",
      "--radius"
    ],
    "subComponents": {
      "CollapsibleContent": {
        "componentName": "CollapsibleContent",
        "fileName": "CollapsibleContent.razor",
        "namespace": "Lumeo",
        "inheritsFrom": null,
        "implements": [],
        "parameters": [
          {
            "name": "Context",
            "type": "Collapsible.CollapsibleContext",
            "default": "default!",
            "description": null,
            "isCascading": true,
            "captureUnmatched": false
          },
          {
            "name": "ChildContent",
            "type": "RenderFragment?",
            "default": null,
            "description": null,
            "isCascading": false,
            "captureUnmatched": false
          },
          {
            "name": "Class",
            "type": "string?",
            "default": null,
            "description": null,
            "isCascading": false,
            "captureUnmatched": false
          },
          {
            "name": "AdditionalAttributes",
            "type": "Dictionary<string, object>?",
            "default": null,
            "description": null,
            "isCascading": false,
            "captureUnmatched": true
          }
        ],
        "events": [],
        "enums": [],
        "records": [],
        "parseFailed": false,
        "parseError": null
      },
      "CollapsibleTrigger": {
        "componentName": "CollapsibleTrigger",
        "fileName": "CollapsibleTrigger.razor",
        "namespace": "Lumeo",
        "inheritsFrom": null,
        "implements": [],
        "parameters": [
          {
            "name": "Context",
            "type": "Collapsible.CollapsibleContext",
            "default": "default!",
            "description": null,
            "isCascading": true,
            "captureUnmatched": false
          },
          {
            "name": "ChildContent",
            "type": "RenderFragment?",
            "default": null,
            "description": null,
            "isCascading": false,
            "captureUnmatched": false
          },
          {
            "name": "Class",
            "type": "string?",
            "default": null,
            "description": null,
            "isCascading": false,
            "captureUnmatched": false
          },
          {
            "name": "AdditionalAttributes",
            "type": "Dictionary<string, object>?",
            "default": null,
            "description": null,
            "isCascading": false,
            "captureUnmatched": true
          }
        ],
        "events": [],
        "enums": [],
        "records": [],
        "parseFailed": false,
        "parseError": null
      }
    },
    "parseFailed": false,
    "parseError": null
  },
  "$schema": "https://lumeo.nativ.sh/registry-component-schema.json",
  "key": "collapsible",
  "docsUrl": "https://lumeo.nativ.sh/components/collapsible",
  "sourceUrl": [
    {
      "file": "UI/Collapsible/Collapsible.razor",
      "url": "https://github.com/Brain2k-0005/Lumeo/tree/master/src/Lumeo/UI/Collapsible/Collapsible.razor"
    },
    {
      "file": "UI/Collapsible/CollapsibleContent.razor",
      "url": "https://github.com/Brain2k-0005/Lumeo/tree/master/src/Lumeo/UI/Collapsible/CollapsibleContent.razor"
    },
    {
      "file": "UI/Collapsible/CollapsibleTrigger.razor",
      "url": "https://github.com/Brain2k-0005/Lumeo/tree/master/src/Lumeo/UI/Collapsible/CollapsibleTrigger.razor"
    }
  ],
  "source": [
    {
      "path": "UI/Collapsible/Collapsible.razor",
      "content": "@namespace Lumeo\r\n\r\n@{\r\n    var context = new CollapsibleContext(Open, EventCallback.Factory.Create(this, Toggle));\r\n}\r\n\r\n<div class=\"@CssClass\" @attributes=\"AdditionalAttributes\">\r\n    <CascadingValue Value=\"context\" IsFixed=\"false\">\r\n        @ChildContent\r\n    </CascadingValue>\r\n</div>\r\n\r\n@code {\r\n    [Parameter] public RenderFragment? ChildContent { get; set; }\r\n    [Parameter] public bool Open { get; set; }\r\n    [Parameter] public EventCallback<bool> OpenChanged { get; set; }\r\n\r\n    [Obsolete(\"Use Open instead. IsOpen will be removed in a future release.\")]\r\n    [Parameter] public bool IsOpen { get => Open; set => Open = value; }\r\n\r\n    [Obsolete(\"Use OpenChanged instead. IsOpenChanged will be removed in a future release.\")]\r\n    [Parameter] public EventCallback<bool> IsOpenChanged { get => OpenChanged; set => OpenChanged = value; }\r\n\r\n    [Parameter] public string? Class { get; set; }\r\n    [Parameter(CaptureUnmatchedValues = true)] public Dictionary<string, object>? AdditionalAttributes { get; set; }\r\n\r\n    private string CssClass => $\"{Class}\".Trim();\r\n\r\n    private async Task Toggle()\r\n    {\r\n        Open = !Open;\r\n        await OpenChanged.InvokeAsync(Open);\r\n    }\r\n\r\n    public record CollapsibleContext(bool IsOpen, EventCallback Toggle);\r\n}\r\n"
    },
    {
      "path": "UI/Collapsible/CollapsibleContent.razor",
      "content": "@namespace Lumeo\n\n@if (Context.IsOpen)\n{\n    <div class=\"@CssClass\" @attributes=\"AdditionalAttributes\">\n        @ChildContent\n    </div>\n}\n\n@code {\n    [CascadingParameter] public Collapsible.CollapsibleContext Context { get; set; } = default!;\n    [Parameter] public RenderFragment? ChildContent { get; set; }\n    [Parameter] public string? Class { get; set; }\n    [Parameter(CaptureUnmatchedValues = true)] public Dictionary<string, object>? AdditionalAttributes { get; set; }\n\n    private string CssClass => $\"animate-accordion-down overflow-hidden {Class}\".Trim();\n}\n"
    },
    {
      "path": "UI/Collapsible/CollapsibleTrigger.razor",
      "content": "@namespace Lumeo\r\n\r\n<div class=\"@CssClass\" role=\"button\" tabindex=\"0\" aria-expanded=\"@Context.IsOpen\" @onclick=\"Context.Toggle\" @onkeydown=\"HandleKeyDown\" @attributes=\"AdditionalAttributes\">\r\n    @ChildContent\r\n</div>\r\n\r\n@code {\r\n    [CascadingParameter] public Collapsible.CollapsibleContext Context { get; set; } = default!;\r\n    [Parameter] public RenderFragment? ChildContent { get; set; }\r\n    [Parameter] public string? Class { get; set; }\r\n    [Parameter(CaptureUnmatchedValues = true)] public Dictionary<string, object>? AdditionalAttributes { get; set; }\r\n\r\n    private string CssClass => $\"cursor-pointer focus-visible:outline-none focus-visible:ring-2 focus-visible:ring-ring focus-visible:ring-offset-2 rounded-sm {Class}\".Trim();\r\n\r\n    private async Task HandleKeyDown(KeyboardEventArgs e)\r\n    {\r\n        if (e.Key == \"Enter\" || e.Key == \" \")\r\n        {\r\n            await Context.Toggle.InvokeAsync();\r\n        }\r\n    }\r\n}\r\n"
    }
  ],
  "slots": [
    {
      "name": "ChildContent",
      "owner": "Collapsible",
      "type": "RenderFragment?",
      "description": null
    },
    {
      "name": "ChildContent",
      "owner": "CollapsibleContent",
      "type": "RenderFragment?",
      "description": null
    },
    {
      "name": "ChildContent",
      "owner": "CollapsibleTrigger",
      "type": "RenderFragment?",
      "description": null
    }
  ],
  "serviceDependencies": [],
  "cascadingDependencies": [
    {
      "name": "Context",
      "type": "Collapsible.CollapsibleContext",
      "required": true
    }
  ],
  "relatedComponents": [
    {
      "name": "CollapsibleContent",
      "reason": "sub-component"
    },
    {
      "name": "CollapsibleTrigger",
      "reason": "sub-component"
    }
  ],
  "keyboardInteractions": [
    {
      "key": "Enter",
      "action": "HandleKeyDown handles Enter in CollapsibleTrigger.razor"
    },
    {
      "key": " ",
      "action": "HandleKeyDown handles   in CollapsibleTrigger.razor"
    }
  ],
  "tests": [],
  "mdSummary": "# Collapsible\r\n\r\nSingle expandable region with animated height transition.\r\n\r\n**Package:** `Lumeo` · **Category:** Navigation\r\n**Docs:** https://lumeo.nativ.sh/components/collapsible\r\n\r\n## Parameters\r\n| Owner | Name | Type | Default | Description |\r\n|---|---|---|---|---|\r\n| Collapsible | ChildContent | `RenderFragment?` | `` |  |\r\n| Collapsible | Open | `bool` | `` |  |\r\n| Collapsible | OpenChanged | `EventCallback<bool>` | `` |  |\r\n| Collapsible | IsOpen | `bool` | `` |  |\r\n| Collapsible | IsOpenChanged | `EventCallback<bool>` | `` |  |\r\n| Collapsible | Class | `string?` | `` |  |\r\n| Collapsible | AdditionalAttributes | `Dictionary<string, object>?` | `` |  |\r\n| CollapsibleContent | Context | `Collapsible.CollapsibleContext` | `default!` |  |\r\n| CollapsibleContent | ChildContent | `RenderFragment?` | `` |  |\r\n| CollapsibleContent | Class | `string?` | `` |  |\r\n| CollapsibleContent | AdditionalAttributes | `Dictionary<string, object>?` | `` |  |\r\n| CollapsibleTrigger | Context | `Collapsible.CollapsibleContext` | `default!` |  |\r\n| CollapsibleTrigger | ChildContent | `RenderFragment?` | `` |  |\r\n| CollapsibleTrigger | Class | `string?` | `` |  |\r\n| CollapsibleTrigger | AdditionalAttributes | `Dictionary<string, object>?` | `` |  |\r\n\r\n## Slots\r\n- `ChildContent` (Collapsible) — RenderFragment slot\r\n- `ChildContent` (CollapsibleContent) — RenderFragment slot\r\n- `ChildContent` (CollapsibleTrigger) — RenderFragment slot\r\n\r\n## Events\r\n- `OpenChanged` (`EventCallback<bool>`)\r\n- `IsOpenChanged` (`EventCallback<bool>`)\r\n\r\n## Sub-components\r\n- `CollapsibleContent`, `CollapsibleTrigger`\r\n\r\n## Cascading values it expects\r\n- `Context` (`Collapsible.CollapsibleContext`)\r\n\r\n## Services it injects\r\n- (none)\r\n\r\n## Keyboard\r\n- `Enter` — HandleKeyDown handles Enter in CollapsibleTrigger.razor\r\n- ` ` — HandleKeyDown handles   in CollapsibleTrigger.razor\r\n\r\n## Example\r\n```razor\r\n<Collapsible />\r\n```\r\n\r\n## CSS variables\r\n`--color-ring`, `--radius`\r\n\r\n## Files\r\n- `UI/Collapsible/Collapsible.razor`\r\n- `UI/Collapsible/CollapsibleContent.razor`\r\n- `UI/Collapsible/CollapsibleTrigger.razor`\r\n"
}